[
{
    "model": "MainApp.color",
    "pk": 1,
    "fields": {
        "name": "red"
    }
},
{
    "model": "MainApp.color",
    "pk": 2,
    "fields": {
        "name": "green"
    }
},
{
    "model": "MainApp.color",
    "pk": 3,
    "fields": {
        "name": "blue"
    }
},
{
    "model": "MainApp.item",
    "pk": 1,
    "fields": {
        "name": "Кроссовки",
        "brand": "abibas",
        "count": 10,
        "description": "Very good shoes",
        "colors": [
            1,
            2
        ]
    }
},
{
    "model": "MainApp.item",
    "pk": 2,
    "fields": {
        "name": "Куртка кожаная",
        "brand": "NoName",
        "count": 2,
        "description": "Nice jacket",
        "colors": [
            1,
            3
        ]
    }
},
{
    "model": "MainApp.item",
    "pk": 3,
    "fields": {
        "name": "Coca-cola 1 литр",
        "brand": "Cocal-cola",
        "count": 12,
        "description": "Tasty coke",
        "colors": []
    }
},
{
    "model": "MainApp.item",
    "pk": 4,
    "fields": {
        "name": "Картофель фри",
        "brand": "ММ",
        "count": 0,
        "description": "Hot Potatoes",
        "colors": []
    }
},
{
    "model": "MainApp.item",
    "pk": 5,
    "fields": {
        "name": "Кепка",
        "brand": "Мaga",
        "count": 124,
        "description": "Universal size",
        "colors": []
    }
}
]
